Metadata-Version: 2.1
Name: riptide-ffa
Version: 0.2.5
Summary: Pulsar searching with the Fast Folding Algorithm (FFA)
Home-page: https://github.com/v-morello/riptide
Author: Vincent Morello
Author-email: vmorello@gmail.com
License: MIT License
Classifier: Programming Language :: Python :: 3.6
Classifier: Programming Language :: Python :: 3.7
Classifier: Programming Language :: Python :: 3.8
Classifier: Programming Language :: Python :: 3.9
Classifier: Programming Language :: C
Classifier: License :: OSI Approved :: MIT License
Classifier: Operating System :: Unix
Classifier: Operating System :: MacOS :: MacOS X
Classifier: Topic :: Scientific/Engineering :: Astronomy
Requires-Python: >=3.6
License-File: LICENSE
Requires-Dist: astropy
Requires-Dist: pandas
Requires-Dist: schema
Requires-Dist: pyyaml
Requires-Dist: threadpoolctl
Requires-Dist: pytest
Requires-Dist: pytest-cov
Requires-Dist: matplotlib
Requires-Dist: numpy
Provides-Extra: develop
Requires-Dist: build; extra == "develop"
Requires-Dist: twine; extra == "develop"
